{
  "type": "Program",
  "body": [
    {
      "type": "ImportDeclaration",
      "specifiers": [
        {
          "type": "ImportDefaultSpecifier",
          "local": {
            "type": "Identifier",
            "name": "Reducer",
            "range": [
              7,
              14
            ],
            "loc": {
              "start": {
                "line": 1,
                "column": 7
              },
              "end": {
                "line": 1,
                "column": 14
              }
            }
          },
          "range": [
            7,
            14
          ],
          "loc": {
            "start": {
              "line": 1,
              "column": 7
            },
            "end": {
              "line": 1,
              "column": 14
            }
          }
        }
      ],
      "source": {
        "type": "Literal",
        "value": "./reducer.js",
        "raw": "'./reducer.js'",
        "range": [
          20,
          34
        ],
        "loc": {
          "start": {
            "line": 1,
            "column": 20
          },
          "end": {
            "line": 1,
            "column": 34
          }
        }
      },
      "range": [
        0,
        35
      ],
      "loc": {
        "start": {
          "line": 1,
          "column": 0
        },
        "end": {
          "line": 1,
          "column": 35
        }
      }
    },
    {
      "type": "ImportDeclaration",
      "specifiers": [
        {
          "type": "ImportDefaultSpecifier",
          "local": {
            "type": "Identifier",
            "name": "Option",
            "range": [
              43,
              49
            ],
            "loc": {
              "start": {
                "line": 2,
                "column": 7
              },
              "end": {
                "line": 2,
                "column": 13
              }
            }
          },
          "range": [
            43,
            49
          ],
          "loc": {
            "start": {
              "line": 2,
              "column": 7
            },
            "end": {
              "line": 2,
              "column": 13
            }
          }
        }
      ],
      "source": {
        "type": "Literal",
        "value": "../option.js",
        "raw": "'../option.js'",
        "range": [
          55,
          69
        ],
        "loc": {
          "start": {
            "line": 2,
            "column": 19
          },
          "end": {
            "line": 2,
            "column": 33
          }
        }
      },
      "range": [
        36,
        70
      ],
      "loc": {
        "start": {
          "line": 2,
          "column": 0
        },
        "end": {
          "line": 2,
          "column": 34
        }
      },
      "trailingComments": [
        {
          "type": "Block",
          "value": "*\n * <b>INTERNAL</b>\n * Yields any events in the context.\n ",
          "range": [
            72,
            135
          ],
          "loc": {
            "start": {
              "line": 4,
              "column": 0
            },
            "end": {
              "line": 7,
              "column": 3
            }
          }
        }
      ]
    },
    {
      "type": "ExportDefaultDeclaration",
      "declaration": {
        "type": "ClassDeclaration",
        "id": {
          "type": "Identifier",
          "name": "AnyEventReducer",
          "range": [
            157,
            172
          ],
          "loc": {
            "start": {
              "line": 8,
              "column": 21
            },
            "end": {
              "line": 8,
              "column": 36
            }
          }
        },
        "superClass": {
          "type": "Identifier",
          "name": "Reducer",
          "range": [
            181,
            188
          ],
          "loc": {
            "start": {
              "line": 8,
              "column": 45
            },
            "end": {
              "line": 8,
              "column": 52
            }
          }
        },
        "body": {
          "type": "ClassBody",
          "body": [
            {
              "type": "MethodDefinition",
              "key": {
                "type": "Identifier",
                "name": "reduce",
                "range": [
                  210,
                  216
                ],
                "loc": {
                  "start": {
                    "line": 10,
                    "column": 2
                  },
                  "end": {
                    "line": 10,
                    "column": 8
                  }
                }
              },
              "value": {
                "type": "FunctionExpression",
                "id": null,
                "params": [
                  {
                    "type": "Identifier",
                    "name": "context",
                    "range": [
                      217,
                      224
                    ],
                    "loc": {
                      "start": {
                        "line": 10,
                        "column": 9
                      },
                      "end": {
                        "line": 10,
                        "column": 16
                      }
                    }
                  }
                ],
                "body": {
                  "type": "BlockStatement",
                  "body": [
                    {
                      "type": "ReturnStatement",
                      "argument": {
                        "type": "CallExpression",
                        "callee": {
                          "type": "MemberExpression",
                          "computed": false,
                          "object": {
                            "type": "Identifier",
                            "name": "context",
                            "range": [
                              239,
                              246
                            ],
                            "loc": {
                              "start": {
                                "line": 11,
                                "column": 11
                              },
                              "end": {
                                "line": 11,
                                "column": 18
                              }
                            }
                          },
                          "property": {
                            "type": "Identifier",
                            "name": "getEvent",
                            "range": [
                              247,
                              255
                            ],
                            "loc": {
                              "start": {
                                "line": 11,
                                "column": 19
                              },
                              "end": {
                                "line": 11,
                                "column": 27
                              }
                            }
                          },
                          "range": [
                            239,
                            255
                          ],
                          "loc": {
                            "start": {
                              "line": 11,
                              "column": 11
                            },
                            "end": {
                              "line": 11,
                              "column": 27
                            }
                          }
                        },
                        "arguments": [],
                        "range": [
                          239,
                          257
                        ],
                        "loc": {
                          "start": {
                            "line": 11,
                            "column": 11
                          },
                          "end": {
                            "line": 11,
                            "column": 29
                          }
                        }
                      },
                      "range": [
                        232,
                        258
                      ],
                      "loc": {
                        "start": {
                          "line": 11,
                          "column": 4
                        },
                        "end": {
                          "line": 11,
                          "column": 30
                        }
                      }
                    }
                  ],
                  "range": [
                    226,
                    262
                  ],
                  "loc": {
                    "start": {
                      "line": 10,
                      "column": 18
                    },
                    "end": {
                      "line": 12,
                      "column": 3
                    }
                  }
                },
                "generator": false,
                "expression": false,
                "range": [
                  216,
                  262
                ],
                "loc": {
                  "start": {
                    "line": 10,
                    "column": 8
                  },
                  "end": {
                    "line": 12,
                    "column": 3
                  }
                }
              },
              "kind": "method",
              "computed": false,
              "range": [
                210,
                262
              ],
              "loc": {
                "start": {
                  "line": 10,
                  "column": 2
                },
                "end": {
                  "line": 12,
                  "column": 3
                }
              },
              "leadingComments": [
                {
                  "type": "Block",
                  "value": "* @ignore ",
                  "range": [
                    193,
                    207
                  ],
                  "loc": {
                    "start": {
                      "line": 9,
                      "column": 2
                    },
                    "end": {
                      "line": 9,
                      "column": 16
                    }
                  }
                }
              ],
              "static": false
            }
          ],
          "range": [
            189,
            264
          ],
          "loc": {
            "start": {
              "line": 8,
              "column": 53
            },
            "end": {
              "line": 13,
              "column": 1
            }
          }
        },
        "range": [
          151,
          264
        ],
        "loc": {
          "start": {
            "line": 8,
            "column": 15
          },
          "end": {
            "line": 13,
            "column": 1
          }
        },
        "leadingComments": [
          {
            "type": "Block",
            "value": "*\n * <b>INTERNAL</b>\n * Yields any events in the context.\n ",
            "range": [
              72,
              135
            ],
            "loc": {
              "start": {
                "line": 4,
                "column": 0
              },
              "end": {
                "line": 7,
                "column": 3
              }
            }
          }
        ],
        "trailingComments": []
      },
      "range": [
        136,
        264
      ],
      "loc": {
        "start": {
          "line": 8,
          "column": 0
        },
        "end": {
          "line": 13,
          "column": 1
        }
      },
      "leadingComments": [
        {
          "type": "Block",
          "value": "*\n * <b>INTERNAL</b>\n * Yields any events in the context.\n ",
          "range": [
            72,
            135
          ],
          "loc": {
            "start": {
              "line": 4,
              "column": 0
            },
            "end": {
              "line": 7,
              "column": 3
            }
          }
        }
      ]
    }
  ],
  "sourceType": "module",
  "range": [
    0,
    264
  ],
  "loc": {
    "start": {
      "line": 1,
      "column": 0
    },
    "end": {
      "line": 13,
      "column": 1
    }
  },
  "comments": [
    {
      "type": "Block",
      "value": "*\n * <b>INTERNAL</b>\n * Yields any events in the context.\n ",
      "range": [
        72,
        135
      ],
      "loc": {
        "start": {
          "line": 4,
          "column": 0
        },
        "end": {
          "line": 7,
          "column": 3
        }
      }
    },
    {
      "type": "Block",
      "value": "* @ignore ",
      "range": [
        193,
        207
      ],
      "loc": {
        "start": {
          "line": 9,
          "column": 2
        },
        "end": {
          "line": 9,
          "column": 16
        }
      }
    }
  ]
}