{
  "type": "Program",
  "body": [
    {
      "type": "ExportDefaultDeclaration",
      "declaration": {
        "type": "ClassDeclaration",
        "id": {
          "type": "Identifier",
          "name": "Reducer",
          "range": [
            79,
            86
          ],
          "loc": {
            "start": {
              "line": 5,
              "column": 21
            },
            "end": {
              "line": 5,
              "column": 28
            }
          }
        },
        "superClass": null,
        "body": {
          "type": "ClassBody",
          "body": [
            {
              "type": "MethodDefinition",
              "key": {
                "type": "Identifier",
                "name": "reduce",
                "range": [
                  344,
                  350
                ],
                "loc": {
                  "start": {
                    "line": 11,
                    "column": 2
                  },
                  "end": {
                    "line": 11,
                    "column": 8
                  }
                }
              },
              "value": {
                "type": "FunctionExpression",
                "id": null,
                "params": [
                  {
                    "type": "Identifier",
                    "name": "context",
                    "range": [
                      351,
                      358
                    ],
                    "loc": {
                      "start": {
                        "line": 11,
                        "column": 9
                      },
                      "end": {
                        "line": 11,
                        "column": 16
                      }
                    }
                  }
                ],
                "body": {
                  "type": "BlockStatement",
                  "body": [
                    {
                      "type": "ThrowStatement",
                      "argument": {
                        "type": "NewExpression",
                        "callee": {
                          "type": "Identifier",
                          "name": "Error",
                          "range": [
                            376,
                            381
                          ],
                          "loc": {
                            "start": {
                              "line": 12,
                              "column": 14
                            },
                            "end": {
                              "line": 12,
                              "column": 19
                            }
                          }
                        },
                        "arguments": [
                          {
                            "type": "Literal",
                            "value": "Abstract method.",
                            "raw": "'Abstract method.'",
                            "range": [
                              382,
                              400
                            ],
                            "loc": {
                              "start": {
                                "line": 12,
                                "column": 20
                              },
                              "end": {
                                "line": 12,
                                "column": 38
                              }
                            }
                          }
                        ],
                        "range": [
                          372,
                          401
                        ],
                        "loc": {
                          "start": {
                            "line": 12,
                            "column": 10
                          },
                          "end": {
                            "line": 12,
                            "column": 39
                          }
                        }
                      },
                      "range": [
                        366,
                        402
                      ],
                      "loc": {
                        "start": {
                          "line": 12,
                          "column": 4
                        },
                        "end": {
                          "line": 12,
                          "column": 40
                        }
                      }
                    }
                  ],
                  "range": [
                    360,
                    406
                  ],
                  "loc": {
                    "start": {
                      "line": 11,
                      "column": 18
                    },
                    "end": {
                      "line": 13,
                      "column": 3
                    }
                  }
                },
                "generator": false,
                "expression": false,
                "range": [
                  350,
                  406
                ],
                "loc": {
                  "start": {
                    "line": 11,
                    "column": 8
                  },
                  "end": {
                    "line": 13,
                    "column": 3
                  }
                }
              },
              "kind": "method",
              "computed": false,
              "range": [
                344,
                406
              ],
              "loc": {
                "start": {
                  "line": 11,
                  "column": 2
                },
                "end": {
                  "line": 13,
                  "column": 3
                }
              },
              "leadingComments": [
                {
                  "type": "Block",
                  "value": "*\n   * Reduces a new value given some previous state if possible.\n   * @param  {ReducerContext} context - The context under which to reduce a new state if possible.\n   * @return {Option<T>} Some value if able to reduce a value otherwise none.\n   ",
                  "range": [
                    91,
                    341
                  ],
                  "loc": {
                    "start": {
                      "line": 6,
                      "column": 2
                    },
                    "end": {
                      "line": 10,
                      "column": 5
                    }
                  }
                }
              ],
              "static": false
            }
          ],
          "range": [
            87,
            408
          ],
          "loc": {
            "start": {
              "line": 5,
              "column": 29
            },
            "end": {
              "line": 14,
              "column": 1
            }
          }
        },
        "range": [
          73,
          408
        ],
        "loc": {
          "start": {
            "line": 5,
            "column": 15
          },
          "end": {
            "line": 14,
            "column": 1
          }
        },
        "leadingComments": [
          {
            "type": "Block",
            "value": "*\n * <b>INTERNAL</b>\n * The base type for reducers.\n ",
            "range": [
              0,
              57
            ],
            "loc": {
              "start": {
                "line": 1,
                "column": 0
              },
              "end": {
                "line": 4,
                "column": 3
              }
            }
          }
        ],
        "trailingComments": []
      },
      "range": [
        58,
        408
      ],
      "loc": {
        "start": {
          "line": 5,
          "column": 0
        },
        "end": {
          "line": 14,
          "column": 1
        }
      },
      "leadingComments": [
        {
          "type": "Block",
          "value": "*\n * <b>INTERNAL</b>\n * The base type for reducers.\n ",
          "range": [
            0,
            57
          ],
          "loc": {
            "start": {
              "line": 1,
              "column": 0
            },
            "end": {
              "line": 4,
              "column": 3
            }
          }
        }
      ]
    }
  ],
  "sourceType": "module",
  "range": [
    58,
    408
  ],
  "loc": {
    "start": {
      "line": 5,
      "column": 0
    },
    "end": {
      "line": 14,
      "column": 1
    }
  },
  "comments": [
    {
      "type": "Block",
      "value": "*\n * <b>INTERNAL</b>\n * The base type for reducers.\n ",
      "range": [
        0,
        57
      ],
      "loc": {
        "start": {
          "line": 1,
          "column": 0
        },
        "end": {
          "line": 4,
          "column": 3
        }
      }
    },
    {
      "type": "Block",
      "value": "*\n   * Reduces a new value given some previous state if possible.\n   * @param  {ReducerContext} context - The context under which to reduce a new state if possible.\n   * @return {Option<T>} Some value if able to reduce a value otherwise none.\n   ",
      "range": [
        91,
        341
      ],
      "loc": {
        "start": {
          "line": 6,
          "column": 2
        },
        "end": {
          "line": 10,
          "column": 5
        }
      }
    }
  ]
}